<?xml version="1.0" encoding="utf-16"?>
<Ac4yObject xmlns:xsi="http://www.w3.org/2001/XMLSchema-instance" xmlns:xsd="http://www.w3.org/2001/XMLSchema">
  <Id>649</Id>
  <GUID>E2CF28D4-0A21-4FC9-B57C-E532D4BBC920</GUID>
  <TemplateGUID>40657D3E-0553-41DB-ACE1-B0B4F9432B77</TemplateGUID>
  <TemplateId>19</TemplateId>
  <TemplateHumanId>tárolt eljárás</TemplateHumanId>
  <TemplatePublicHumanId>tárolt eljárás</TemplatePublicHumanId>
  <TemplateSimpledHumanId>tárolt eljárás</TemplateSimpledHumanId>
  <TemplateNamespace />
  <HumanId>Bev_Mvisz_H142</HumanId>
  <PublicHumanId>Bev_Mvisz_H142</PublicHumanId>
  <SimpledHumanId>BEVMVISZH142</SimpledHumanId>
  <Namespace />
</Ac4yObject>