<?xml version="1.0" encoding="utf-16"?>
<Ac4yObject xmlns:xsi="http://www.w3.org/2001/XMLSchema-instance" xmlns:xsd="http://www.w3.org/2001/XMLSchema">
  <Id>1000</Id>
  <GUID>63B38665-EBF7-4153-9D47-E59ED61CF7CF</GUID>
  <TemplateGUID>40657D3E-0553-41DB-ACE1-B0B4F9432B77</TemplateGUID>
  <TemplateId>19</TemplateId>
  <TemplateHumanId>tárolt eljárás</TemplateHumanId>
  <TemplatePublicHumanId>tárolt eljárás</TemplatePublicHumanId>
  <TemplateSimpledHumanId>TAROLTELJARAS</TemplateSimpledHumanId>
  <TemplateNamespace />
  <HumanId>Szo_EszlaFelulvizsgalat</HumanId>
  <PublicHumanId>Szo_EszlaFelulvizsgalat</PublicHumanId>
  <SimpledHumanId>SZOESZLAFELULVIZSGALAT</SimpledHumanId>
  <Namespace />
</Ac4yObject>